{
  "_embedded": {
    "attractions": [
      {
        "_links": {
          "self": {
            "href": "/discovery/v2/attractions/K8vZ9171tJV?locale=en-us"
          }
        },
        "classifications": [
          {
            "family": false,
            "genre": {
              "id": "KnvZfZ7vA7d",
              "name": "Martial Arts"
            },
            "primary": true,
            "segment": {
              "id": "KZFzniwnSyZfZ7v7nE",
              "name": "Sports"
            },
            "subGenre": {
              "id": "KZazBEonSMnZfZ7vFIE",
              "name": "Mixed Martial Arts"
            },
            "subType": {
              "id": "KZFzBErXgnZfZ7v7lJ",
              "name": "Undefined"
            },
            "type": {
              "id": "KZAyXgnZfZ7v7nI",
              "name": "Undefined"
            }
          }
        ],
        "id": "K8vZ9171tJV",
        "images": [
          {
            "fallback": false,
            "height": 639,
            "ratio": "16_9",
            "url": "https://s1.ticketm.net/dam/a/138/09f8507b-e5bd-400f-8363-8c3b83e82138_RETINA_LANDSCAPE_16_9.jpg",
            "width": 1136
          },
          {
            "fallback": false,
            "height": 115,
            "ratio": "16_9",
            "url": "https://s1.ticketm.net/dam/a/138/09f8507b-e5bd-400f-8363-8c3b83e82138_EVENT_DETAIL_PAGE_16_9.jpg",
            "width": 205
          },
          {
            "fallback": false,
            "height": 1365,
            "ratio": "16_9",
            "url": "https://s1.ticketm.net/dam/a/138/09f8507b-e5bd-400f-8363-8c3b83e82138_SOURCE",
            "width": 2426
          },
          {
            "fallback": false,
            "height": 576,
            "ratio": "16_9",
            "url": "https://s1.ticketm.net/dam/a/138/09f8507b-e5bd-400f-8363-8c3b83e82138_TABLET_LANDSCAPE_16_9.jpg",
            "width": 1024
          },
          {
            "fallback": false,
            "height": 203,
            "ratio": "3_2",
            "url": "https://s1.ticketm.net/dam/a/138/09f8507b-e5bd-400f-8363-8c3b83e82138_ARTIST_PAGE_3_2.jpg",
            "width": 305
          },
          {
            "fallback": false,
            "height": 683,
            "ratio": "3_2",
            "url": "https://s1.ticketm.net/dam/a/138/09f8507b-e5bd-400f-8363-8c3b83e82138_TABLET_LANDSCAPE_3_2.jpg",
            "width": 1024
          },
          {
            "fallback": false,
            "height": 427,
            "ratio": "3_2",
            "url": "https://s1.ticketm.net/dam/a/138/09f8507b-e5bd-400f-8363-8c3b83e82138_RETINA_PORTRAIT_3_2.jpg",
            "width": 640
          },
          {
            "fallback": false,
            "height": 360,
            "ratio": "16_9",
            "url": "https://s1.ticketm.net/dam/a/138/09f8507b-e5bd-400f-8363-8c3b83e82138_RETINA_PORTRAIT_16_9.jpg",
            "width": 640
          },
          {
            "fallback": false,
            "height": 1152,
            "ratio": "16_9",
            "url": "https://s1.ticketm.net/dam/a/138/09f8507b-e5bd-400f-8363-8c3b83e82138_TABLET_LANDSCAPE_LARGE_16_9.jpg",
            "width": 2048
          },
          {
            "fallback": false,
            "height": 56,
            "ratio": "16_9",
            "url": "https://s1.ticketm.net/dam/a/138/09f8507b-e5bd-400f-8363-8c3b83e82138_RECOMENDATION_16_9.jpg",
            "width": 100
          },
          {
            "fallback": false,
            "height": 225,
            "ratio": "4_3",
            "url": "https://s1.ticketm.net/dam/a/138/09f8507b-e5bd-400f-8363-8c3b83e82138_CUSTOM.jpg",
            "width": 305
          }
        ],
        "locale": "en-us",
        "name": "Ultimate Fighting Championship - UFC",
        "test": false,
        "type": "attraction",
        "upcomingEvents": {
          "_filtered": 0,
          "_total": 4,
          "ticketmaster": 4
        },
        "url": "https://www.ticketmaster.com.au/ultimate-fighting-championship-ufc-tickets/artist/806762"
      }
    ],
    "venues": [
      {
        "_links": {
          "self": {
            "href": "/discovery/v2/venues/KovZpZAJtFaA?locale=en-us"
          }
        },
        "accessibleSeatingDetail": "This is an accessible venue.",
        "address": {
          "line1": "601 Biscayne Blvd"
        },
        "aliases": [
          "americanairlines arena",
          "american airlines arena"
        ],
        "boxOfficeInfo": {
          "acceptedPaymentDetail": "Visa, MasterCard, Discover, American Express",
          "openHoursDetail": "Kaseya Center will only be open on event days. Arena Box Office Information (786) 777-1250",
          "phoneNumberDetail": "Miami HEAT & Arena Event Sales Information: \u2022 Miami HEAT Season Tickets & Partial Plans (786) 777 HOOP \u2022 Miami HEAT Group Tickets (786) 777 DUNK \u2022 Miami HEAT Premium Seats (Courtside/Flagship/Suites/Loges) (786) 777 4320 \u2022 Arena Event Suite Sales (786) 777 1000 \u2022 Group Ticket & Fundraising Opportunities for Arena Family Shows (786) 777 4FUN (4386)",
          "willCallDetail": "Will Call is located at the Ticketmaster Box Office on the North Side of the Arena located between Gates 3 & 4. Valid ID required to pick up Will Call Tickets"
        },
        "city": {
          "name": "Miami"
        },
        "country": {
          "countryCode": "US",
          "name": "United States Of America"
        },
        "dmas": [
          {
            "id": 200
          },
          {
            "id": 334
          },
          {
            "id": 412
          }
        ],
        "generalInfo": {
          "generalRule": "For all you need to know from A-Z, please log on to: www.kaseyacenter.com"
        },
        "id": "KovZpZAJtFaA",
        "locale": "en-us",
        "location": {
          "latitude": "25.781232",
          "longitude": "-80.187805"
        },
        "markets": [
          {
            "id": "15",
            "name": "Miami"
          },
          {
            "id": "51",
            "name": "All of US"
          }
        ],
        "name": "Kaseya Center",
        "parkingDetail": "Suggested Parking Information: http://d2yex7fc50u2fe.cloudfront.net/pdfs/ Event_parking_options.pdf",
        "postalCode": "33132",
        "social": {
          "twitter": {
            "handle": "@AAarena"
          }
        },
        "state": {
          "name": "Florida",
          "stateCode": "FL"
        },
        "test": false,
        "timezone": "America/New_York",
        "type": "venue",
        "upcomingEvents": {
          "_filtered": 0,
          "_total": 48,
          "ticketmaster": 48
        },
        "url": "https://www.ticketmaster.com/kaseya-center-tickets-miami/venue/106601"
      }
    ]
  },
  "_links": {
    "attractions": [
      {
        "href": "/discovery/v2/attractions/K8vZ9171tJV?locale=en-us"
      }
    ],
    "self": {
      "href": "/discovery/v2/events/vvG1VZ9ypQkobZ?locale=en-us"
    },
    "venues": [
      {
        "href": "/discovery/v2/venues/KovZpZAJtFaA?locale=en-us"
      }
    ]
  },
  "accessibility": {
    "ticketLimit": 4
  },
  "ageRestrictions": {
    "legalAgeEnforced": false
  },
  "classifications": [
    {
      "family": false,
      "genre": {
        "id": "KnvZfZ7vA7d",
        "name": "Martial Arts"
      },
      "primary": true,
      "segment": {
        "id": "KZFzniwnSyZfZ7v7nE",
        "name": "Sports"
      },
      "subGenre": {
        "id": "KZazBEonSMnZfZ7vFIE",
        "name": "Mixed Martial Arts"
      },
      "subType": {
        "id": "KZFzBErXgnZfZ7v7lJ",
        "name": "Undefined"
      },
      "type": {
        "id": "KZAyXgnZfZ7v7nI",
        "name": "Undefined"
      }
    }
  ],
  "dates": {
    "spanMultipleDays": false,
    "start": {
      "dateTBA": false,
      "dateTBD": false,
      "dateTime": "2024-03-10T00:15:00Z",
      "localDate": "2024-03-09",
      "localTime": "19:15:00",
      "noSpecificTime": false,
      "timeTBA": false
    },
    "status": {
      "code": "onsale"
    },
    "timezone": "America/New_York"
  },
  "id": "vvG1VZ9ypQkobZ",
  "images": [
    {
      "fallback": false,
      "height": 639,
      "ratio": "16_9",
      "url": "https://s1.ticketm.net/dam/a/138/09f8507b-e5bd-400f-8363-8c3b83e82138_RETINA_LANDSCAPE_16_9.jpg",
      "width": 1136
    },
    {
      "fallback": false,
      "height": 115,
      "ratio": "16_9",
      "url": "https://s1.ticketm.net/dam/a/138/09f8507b-e5bd-400f-8363-8c3b83e82138_EVENT_DETAIL_PAGE_16_9.jpg",
      "width": 205
    },
    {
      "fallback": false,
      "height": 1365,
      "ratio": "16_9",
      "url": "https://s1.ticketm.net/dam/a/138/09f8507b-e5bd-400f-8363-8c3b83e82138_SOURCE",
      "width": 2426
    },
    {
      "fallback": false,
      "height": 576,
      "ratio": "16_9",
      "url": "https://s1.ticketm.net/dam/a/138/09f8507b-e5bd-400f-8363-8c3b83e82138_TABLET_LANDSCAPE_16_9.jpg",
      "width": 1024
    },
    {
      "fallback": false,
      "height": 203,
      "ratio": "3_2",
      "url": "https://s1.ticketm.net/dam/a/138/09f8507b-e5bd-400f-8363-8c3b83e82138_ARTIST_PAGE_3_2.jpg",
      "width": 305
    },
    {
      "fallback": false,
      "height": 683,
      "ratio": "3_2",
      "url": "https://s1.ticketm.net/dam/a/138/09f8507b-e5bd-400f-8363-8c3b83e82138_TABLET_LANDSCAPE_3_2.jpg",
      "width": 1024
    },
    {
      "fallback": false,
      "height": 427,
      "ratio": "3_2",
      "url": "https://s1.ticketm.net/dam/a/138/09f8507b-e5bd-400f-8363-8c3b83e82138_RETINA_PORTRAIT_3_2.jpg",
      "width": 640
    },
    {
      "fallback": false,
      "height": 360,
      "ratio": "16_9",
      "url": "https://s1.ticketm.net/dam/a/138/09f8507b-e5bd-400f-8363-8c3b83e82138_RETINA_PORTRAIT_16_9.jpg",
      "width": 640
    },
    {
      "fallback": false,
      "height": 1152,
      "ratio": "16_9",
      "url": "https://s1.ticketm.net/dam/a/138/09f8507b-e5bd-400f-8363-8c3b83e82138_TABLET_LANDSCAPE_LARGE_16_9.jpg",
      "width": 2048
    },
    {
      "fallback": false,
      "height": 56,
      "ratio": "16_9",
      "url": "https://s1.ticketm.net/dam/a/138/09f8507b-e5bd-400f-8363-8c3b83e82138_RECOMENDATION_16_9.jpg",
      "width": 100
    },
    {
      "fallback": false,
      "height": 225,
      "ratio": "4_3",
      "url": "https://s1.ticketm.net/dam/a/138/09f8507b-e5bd-400f-8363-8c3b83e82138_CUSTOM.jpg",
      "width": 305
    }
  ],
  "locale": "en-us",
  "name": "UFC 299 Miami",
  "pleaseNote": "Card/Timing Subject to Change",
  "priceRanges": [
    {
      "currency": "USD",
      "max": 6000.0,
      "min": 250.0,
      "type": "standard"
    }
  ],
  "products": [
    {
      "classifications": [
        {
          "family": false,
          "genre": {
            "id": "KnvZfZ7v7ll",
            "name": "Undefined"
          },
          "primary": true,
          "segment": {
            "id": "KZFzniwnSyZfZ7v7n1",
            "name": "Miscellaneous"
          },
          "subGenre": {
            "id": "KZazBEonSMnZfZ7vAv1",
            "name": "Undefined"
          },
          "subType": {
            "id": "KZFzBErXgnZfZ7vAe6",
            "name": "Membership"
          },
          "type": {
            "id": "KZAyXgnZfZ7v7l6",
            "name": "Merchandise"
          }
        }
      ],
      "id": "vvG1VZbeE2HoXS",
      "name": "UFC Fight Club Champion Membership",
      "type": "Upsell",
      "url": "https://www.ticketmaster.com/ufc-fight-club-champion-membership-miami-florida-03-09-2024/event/0D006029CFF11FB3"
    },
    {
      "classifications": [
        {
          "family": false,
          "genre": {
            "id": "KnvZfZ7v7ll",
            "name": "Undefined"
          },
          "primary": true,
          "segment": {
            "id": "KZFzniwnSyZfZ7v7n1",
            "name": "Miscellaneous"
          },
          "subGenre": {
            "id": "KZazBEonSMnZfZ7vAv1",
            "name": "Undefined"
          },
          "subType": {
            "id": "KZFzBErXgnZfZ7vAe6",
            "name": "Membership"
          },
          "type": {
            "id": "KZAyXgnZfZ7v7l6",
            "name": "Merchandise"
          }
        }
      ],
      "id": "vvG1VZbeE2w-XR",
      "name": "UFC Fight Club Legend Membership",
      "type": "Upsell",
      "url": "https://www.ticketmaster.com/ufc-fight-club-legend-membership-miami-florida-03-09-2024/event/0D006029CFCA1FAF"
    },
    {
      "classifications": [
        {
          "family": false,
          "genre": {
            "id": "KnvZfZ7v7ll",
            "name": "Undefined"
          },
          "primary": true,
          "segment": {
            "id": "KZFzniwnSyZfZ7v7n1",
            "name": "Miscellaneous"
          },
          "subGenre": {
            "id": "KZazBEonSMnZfZ7vAv1",
            "name": "Undefined"
          },
          "subType": {
            "id": "KZFzBErXgnZfZ7vAe6",
            "name": "Membership"
          },
          "type": {
            "id": "KZAyXgnZfZ7v7l6",
            "name": "Merchandise"
          }
        }
      ],
      "id": "vvG1VZbeE87sXU",
      "name": "UFC Fight Club Challenger Membership",
      "type": "Upsell",
      "url": "https://www.ticketmaster.com/ufc-fight-club-challenger-membership-miami-florida-03-09-2024/event/0D006029D0131FB6"
    },
    {
      "classifications": [
        {
          "family": false,
          "genre": {
            "id": "KnvZfZ7v7ll",
            "name": "Undefined"
          },
          "primary": true,
          "segment": {
            "id": "KZFzniwnSyZfZ7v7n1",
            "name": "Miscellaneous"
          },
          "subGenre": {
            "id": "KZazBEonSMnZfZ7vAv1",
            "name": "Undefined"
          },
          "subType": {
            "id": "KZFzBErXgnZfZ7vAFk",
            "name": "Premier"
          },
          "type": {
            "id": "KZAyXgnZfZ7vAva",
            "name": "Parking"
          }
        }
      ],
      "id": "vvG1VZbeJpzoGU",
      "name": "Kaseya Center Parking: UFC 299 Miami",
      "type": "Parking",
      "url": "https://www.ticketmaster.com/kaseya-center-parking-ufc-299-miami-miami-florida-03-09-2024/event/0D00602996E11336"
    }
  ],
  "sales": {
    "presales": [
      {
        "endDateTime": "2024-01-12T14:00:00Z",
        "name": "UFC Presales",
        "startDateTime": "2024-01-11T15:00:00Z"
      },
      {
        "endDateTime": "2024-01-11T14:00:00Z",
        "name": "Fight Club Presale and Bundle",
        "startDateTime": "2024-01-10T15:00:00Z"
      },
      {
        "endDateTime": "2024-01-12T14:00:00Z",
        "name": "Newsletter Presale",
        "startDateTime": "2024-01-11T15:00:00Z"
      },
      {
        "endDateTime": "2024-01-12T14:00:00Z",
        "name": "Official Platinum Presale",
        "startDateTime": "2024-01-10T15:00:00Z"
      },
      {
        "endDateTime": "2024-03-04T02:15:00Z",
        "name": "Official Platinum Onsale",
        "startDateTime": "2024-01-12T15:00:00Z"
      }
    ],
    "public": {
      "endDateTime": "2024-03-10T02:15:00Z",
      "startDateTime": "2024-01-12T15:00:00Z",
      "startTBA": false,
      "startTBD": false
    }
  },
  "seatmap": {
    "staticUrl": "https://maps.ticketmaster.com/maps/geometry/3/event/0D005F959A191600/staticImage?type=png&systemId=HOST"
  },
  "test": false,
  "ticketLimit": {
    "info": "There is an 8 ticket limit for the Fight Club Presale and Newsletter Presale."
  },
  "ticketing": {
    "allInclusivePricing": {
      "enabled": false
    },
    "safeTix": {
      "enabled": true
    }
  },
  "type": "event",
  "url": "https://www.ticketmaster.com/ufc-299-miami-miami-florida-03-09-2024/event/0D005F959A191600"
}